{
  "version": "7",
  "dialect": "sqlite",
  "entries": [
    {
      "idx": 0,
      "version": "6",
      "when": 1766828416526,
      "tag": "0000_first-migration",
      "breakpoints": true
    },
    {
      "idx": 1,
      "version": "6",
      "when": 1766895149380,
      "tag": "0001_update-manga-schema",
      "breakpoints": true
    },
    {
      "idx": 2,
      "version": "6",
      "when": 1766938011641,
      "tag": "0002_adding-new-manga-column",
      "breakpoints": true
    }
  ]
}